{
  "tables": [
    {
      "config": {
        "columnsConfig": {
          "name": 912,
          "attack": 100,
          "defence": 100,
          "health": 100
        },
        "pageSize": 25
      },
      "tableName": "TavernaHeroesTable",
      "userId": "e046",
      "id": "18d3"
    }
  ],
  "users": [
    {
      "id": "e046",
      "login": "rest",
      "password": "rest",
      "online": {
        "onlineTime": 1056240,
        "claimedRewards": ["2", "4", "8", "12"],
        "lastLoyaltyBonus": "12/27/2025"
      },
      "currency": {
        "gold": 1926,
        "silver": 5241,
        "copper": 3461777
      },
      "createdAt": 1756640349588,
      "depositId": "61ec"
    }
  ],
  "dailyReward": [
    {
      "id": "ab59",
      "userId": "e046",
      "day": 12,
      "totalDays": 97,
      "lastLogin": "12/27/2025"
    }
  ],
  "giftTrip": [
    {
      "id": "16b0",
      "userId": "e046",
      "lastLogin": "12/27/2025"
    }
  ],
  "dailyBoss": [
    {
      "id": "16b0",
      "userId": "e046",
      "lastLogin": "12/27/2025"
    }
  ],
  "deposits": [
    {
      "copper": 69000000,
      "depositDay": 1765711225574,
      "duration": 120,
      "gold": 29000,
      "silver": 72000,
      "id": "61ec",
      "userId": "e046"
    }
  ]
}
