{
  "users": [
    {
      "id": "4b82",
      "login": "admin",
      "password": "admin",
      "online": {
        "onlineTime": 0,
        "claimedRewards": []
      }
    },
    {
      "id": "2ac5",
      "login": "test",
      "password": "test",
      "online": {
        "onlineTime": 0,
        "claimedRewards": []
      }
    },
    {
      "id": "e046",
      "login": "rest",
      "password": "rest",
      "online": {
        "onlineTime": 120600,
        "claimedRewards": [
          "2",
          "4",
          "8",
          "12"
        ],
        "lastLoyaltyBonus": "10/10/2025"
      },
      "currency": {
        "gold": 320,
        "silver": 41441,
        "copper": 34354070
      },
      "createdAt": 1756640349588,
      "depositId": "61ec"
    }
  ],
  "dailyReward": [
    {
      "id": "6fe2",
      "userId": "2ac5",
      "day": 25,
      "totalDays": 25,
      "lastLogin": "12/13/2024"
    },
    {
      "id": "ab59",
      "userId": "e046",
      "day": 20,
      "totalDays": 49,
      "lastLogin": "10/12/2025"
    }
  ],
  "giftTrip": [
    {
      "id": "6fe2",
      "userId": "2ac5",
      "lastLogin": "10/29/2024"
    },
    {
      "id": "16b0",
      "userId": "e046",
      "lastLogin": "10/12/2025"
    }
  ],
  "deposits": [
    {
      "copper": 0,
      "depositDay": 1760186836843,
      "duration": 3,
      "gold": 18000,
      "silver": 0,
      "id": "61ec",
      "userId": "e046"
    }
  ]
}